lpr_test2/__init__.py
lpr_test2/test.py
lpr_test2-1.0.0.dist-info/licenses/LICENCE
lpr_test2-1.0.0.dist-info/METADATA
lpr_test2-1.0.0.dist-info/WHEEL
lpr_test2-1.0.0.dist-info/top_level.txt
lpr_test2-1.0.0.dist-info/RECORD
