Metadata-Version: 2.4
Name: lpr-test2
Version: 1.0.0
Summary: test package
Author: lpr
Author-email: 948392651@qq.com
License-File: LICENCE
Requires-Dist: lpr-test1
Dynamic: author
Dynamic: author-email
Dynamic: description
Dynamic: description-content-type
Dynamic: license-file
Dynamic: requires-dist
Dynamic: summary
